clr.py
pythonnet/__init__.py
pythonnet/runtime/Python.Runtime.deps.json
pythonnet/runtime/Python.Runtime.dll
pythonnet/runtime/Python.Runtime.pdb
pythonnet/runtime/Python.Runtime.xml
pythonnet-3.0.4.dist-info/AUTHORS.md
pythonnet-3.0.4.dist-info/LICENSE
pythonnet-3.0.4.dist-info/METADATA
pythonnet-3.0.4.dist-info/WHEEL
pythonnet-3.0.4.dist-info/top_level.txt
pythonnet-3.0.4.dist-info/RECORD
