Metadata-Version: 2.1
Name: pythonnet
Version: 3.0.4
Summary: .NET and Mono integration for Python
Author-email: "The Contributors of the Python.NET Project" <pythonnet@python.org>
License: MIT
Project-URL: Homepage, https://pythonnet.github.io/
Project-URL: Sources, https://github.com/pythonnet/pythonnet
Classifier: Development Status :: 5 - Production/Stable
Classifier: Intended Audience :: Developers
Classifier: License :: OSI Approved :: MIT License
Classifier: Programming Language :: C#
Classifier: Programming Language :: Python :: 3
Classifier: Programming Language :: Python :: 3.7
Classifier: Programming Language :: Python :: 3.8
Classifier: Programming Language :: Python :: 3.9
Classifier: Programming Language :: Python :: 3.10
Classifier: Programming Language :: Python :: 3.11
Classifier: Programming Language :: Python :: 3.12
Classifier: Operating System :: Microsoft :: Windows
Classifier: Operating System :: POSIX :: Linux
Classifier: Operating System :: MacOS :: MacOS X
Requires-Python: <3.13,>=3.7
License-File: LICENSE
License-File: AUTHORS.md
Requires-Dist: clr_loader<0.3.0,>=0.2.6
